guess_simulator/__init__.py
guess_simulator/cli.py
guess_simulator/config.py
guess_simulator/game.py
guess_simulator/logger.py
guess_simulator/storage.py
guess_simulator/validator.py
omar_ayush_guess_simulator-1.0.0.dist-info/METADATA
omar_ayush_guess_simulator-1.0.0.dist-info/WHEEL
omar_ayush_guess_simulator-1.0.0.dist-info/entry_points.txt
omar_ayush_guess_simulator-1.0.0.dist-info/top_level.txt
omar_ayush_guess_simulator-1.0.0.dist-info/RECORD
