Metadata-Version: 2.4
Name: omar-ayush-guess-simulator
Version: 1.0.0
Summary: A production-grade CLI for probability-guided number guessing games
Author-email: Omar Ayush <omar.ayush@example.com>
License: MIT
Classifier: Development Status :: 4 - Beta
Classifier: Intended Audience :: Education
Classifier: Topic :: Games/Entertainment :: Puzzle Games
Classifier: Programming Language :: Python :: 3
Requires-Python: >=3.7
